<annotation>
	<folder>N</folder>
	<filename>N.b457cb72-a959-11ec-a060-1856807ac663.jpg</filename>
	<path>C:\Users\danie\PycharmProjects\RealTimeObjectDetection\Tensorflow\workspace\images\collectedimages\N\N.b457cb72-a959-11ec-a060-1856807ac663.jpg</path>
	<source>
		<database>Unknown</database>
	</source>
	<size>
		<width>640</width>
		<height>480</height>
		<depth>3</depth>
	</size>
	<segmented>0</segmented>
	<object>
		<name>N</name>
		<pose>Unspecified</pose>
		<truncated>0</truncated>
		<difficult>0</difficult>
		<bndbox>
			<xmin>487</xmin>
			<ymin>175</ymin>
			<xmax>577</xmax>
			<ymax>270</ymax>
		</bndbox>
	</object>
</annotation>
